setup.cfg
setup.py
vse/__init__.py
vse/comparator.py
vse/engine.py
vse/error.py
vse/index.py
vse/ranker.py
vse/utils.py
vse.egg-info/PKG-INFO
vse.egg-info/SOURCES.txt
vse.egg-info/dependency_links.txt
vse.egg-info/requires.txt
vse.egg-info/top_level.txt