Metadata-Version: 1.1
Name: vse
Version: 0.1.4
Summary: Configurable visual search engine based on the OpenCV
Home-page: https://github.com/mkpaszkiewicz/vse
Author: Marcin K. Paszkiewicz
Author-email: mkpaszkiewicz@gmail.com
License: UNKNOWN
Download-URL: https://github.com/mkpaszkiewicz/vse/tarball/0.1.3
Keywords: visual,search,engine,computer,vision
Platform: UNKNOWN
